state_machine/__init__.py
state_machine/core.py
state_machine/decorator_manager.py
state_machine/decorator_protocols.py
state_machine/decorators.py
state_machine/defs.py
state_machine/machine_protocols.py
state_machine/router.py
state_machine/utils.py
vention_state_machine-0.3.1.dist-info/METADATA
vention_state_machine-0.3.1.dist-info/WHEEL
vention_state_machine-0.3.1.dist-info/RECORD
