Metadata-Version: 2.1
Name: vention-state-machine
Version: 0.3.1
Summary: Declarative state machine framework for machine apps
License: Proprietary
Author: VentionCo
Requires-Python: >=3.10,<3.11
Classifier: License :: Other/Proprietary License
Classifier: Programming Language :: Python :: 3
Classifier: Programming Language :: Python :: 3.10
Requires-Dist: asyncio (>=3.4.3,<4.0.0)
Requires-Dist: coverage (>=7.10.1,<8.0.0)
Requires-Dist: fastapi (==0.121.1)
Requires-Dist: graphviz (>=0.21,<0.22)
Requires-Dist: httpx (>=0.28.1,<0.29.0)
Requires-Dist: transitions (>=0.9.3,<0.10.0)
Requires-Dist: uvicorn (>=0.35.0,<0.36.0)
